pygifgenerator_testver/__init__.py
pygifgenerator_testver/gifgenerator.py
pygifgenerator_testver-1.0.0.dist-info/licenses/LICENSE
pygifgenerator_testver-1.0.0.dist-info/METADATA
pygifgenerator_testver-1.0.0.dist-info/WHEEL
pygifgenerator_testver-1.0.0.dist-info/top_level.txt
pygifgenerator_testver-1.0.0.dist-info/RECORD
