Metadata-Version: 2.4
Name: pygifgenerator_testver
Version: 1.0.0
Summary: Test package for distribution
Home-page: 
Download-URL: 
Author: Monstro
Author-email: 
Keywords: GIFGENERATOR,gifgenerator
Classifier: Programming Language :: Python :: 3
Classifier: License :: OSI Approved :: MIT License
Classifier: Operating System :: OS Independent
Requires-Python: >=3
License-File: LICENSE
Requires-Dist: pillow
Dynamic: author
Dynamic: classifier
Dynamic: keywords
Dynamic: license-file
Dynamic: requires-dist
Dynamic: requires-python
Dynamic: summary
